icquantum/__init__.py
icquantum/circuit_cache.py
icquantum/main_cli.py
icquantum/postprocessing.py
icquantum/py.typed
icquantum/qiskit.py
icquantum/session.py
icquantum/simulation.py
icquantum-0.0.5.dist-info/LICENSE
icquantum-0.0.5.dist-info/METADATA
icquantum-0.0.5.dist-info/WHEEL
icquantum-0.0.5.dist-info/entry_points.txt
icquantum-0.0.5.dist-info/top_level.txt
icquantum-0.0.5.dist-info/RECORD
