Metadata-Version: 2.1
Name: icquantum
Version: 0.0.5
Summary: Support tooling for Quantum Computing simulations.
Author-email: "Ben Collingwood, Irish Centre for High End Computing" <benjamin.collingwood@ichec.ie>
Project-URL: Repository, https://git.ichec.ie/performance/toolshed/icquantum
Project-URL: Homepage, https://git.ichec.ie/performance/toolshed/icquantum
Keywords: Quantum Computing,Workflow,HPC
Classifier: Development Status :: 3 - Alpha
Classifier: Programming Language :: Python :: 3
Classifier: License :: OSI Approved :: GNU General Public License v3 or later (GPLv3+)
Classifier: Operating System :: OS Independent
Classifier: Topic :: System :: Distributed Computing
Requires-Python: >=3.8
License-File: LICENSE
Requires-Dist: icflow==0.1.2
Requires-Dist: qiskit-aer
Requires-Dist: mqt.bench
Provides-Extra: test
Requires-Dist: pytest; extra == "test"
Requires-Dist: pytest-cov; extra == "test"
Requires-Dist: pytest-sugar; extra == "test"
Requires-Dist: black; extra == "test"
Requires-Dist: flake8; extra == "test"
Requires-Dist: pylint; extra == "test"
Requires-Dist: mypy; extra == "test"
